single_hurnet_core/__init__.py
single_hurnet_core/single_hurnet_core.py
single_hurnet_core-1.0.0.dist-info/LICENSE.txt
single_hurnet_core-1.0.0.dist-info/METADATA
single_hurnet_core-1.0.0.dist-info/WHEEL
single_hurnet_core-1.0.0.dist-info/top_level.txt
single_hurnet_core-1.0.0.dist-info/RECORD
